{
  "Id": 2,
  "Name": "Equestria8x6",
  "Columns": 8,
  "Rows": 6,
  "EntityList": {
    "Chest0": {
      "EntityID": 0,
      "MapID": 0,
      "X": 1,
      "Y": 2,
      "Name": "Chest0",
      "ImagePath": "C:\\Users\\Victorus\\source\\repos\\milkosek\\Project_RPGWonder\\RPGWonder\\src\\asset\\chest.png",
      "Id": 0,
      "Type": null,
      "Description": null,
      "Src": null
    },
    "Chest1": {
      "EntityID": 0,
      "MapID": 0,
      "X": 2,
      "Y": 2,
      "Name": "Chest1",
      "ImagePath": "C:\\Users\\Victorus\\source\\repos\\milkosek\\Project_RPGWonder\\RPGWonder\\src\\asset\\chest.png",
      "Id": 0,
      "Type": null,
      "Description": null,
      "Src": null
    },
    "Chest2": {
      "EntityID": 0,
      "MapID": 0,
      "X": 3,
      "Y": 1,
      "Name": "Chest2",
      "ImagePath": "C:\\Users\\Victorus\\source\\repos\\milkosek\\Project_RPGWonder\\RPGWonder\\src\\asset\\chest.png",
      "Id": 0,
      "Type": null,
      "Description": null,
      "Src": null
    }
  }
}